mllearner/__init__.py
mllearner/data.py
mllearner/evaluation.py
mllearner/models.py
mllearner/training.py
mllearner/utils.py
mllearner/visualization.py
mllearner-0.1.0.dist-info/METADATA
mllearner-0.1.0.dist-info/WHEEL
mllearner-0.1.0.dist-info/top_level.txt
mllearner-0.1.0.dist-info/RECORD
