Metadata-Version: 2.4
Name: mllearner
Version: 0.1.0
Summary: A comprehensive ML package for learners - providing utilities for data preprocessing, model building, training, and evaluation
Author-email: Harsh Tambade <harsh@example.com>
License: MIT
Project-URL: Homepage, https://github.com/HarshTambade/ML-Learning-Hub
Project-URL: Documentation, https://github.com/HarshTambade/ML-Learning-Hub/wiki
Project-URL: Repository, https://github.com/HarshTambade/ML-Learning-Hub
Project-URL: Issues, https://github.com/HarshTambade/ML-Learning-Hub/issues
Keywords: machine-learning,data-science,ml-framework,learning
Classifier: Development Status :: 4 - Beta
Classifier: Intended Audience :: Developers
Classifier: Intended Audience :: Education
Classifier: License :: OSI Approved :: MIT License
Classifier: Programming Language :: Python :: 3
Classifier: Programming Language :: Python :: 3.8
Classifier: Programming Language :: Python :: 3.9
Classifier: Programming Language :: Python :: 3.10
Classifier: Programming Language :: Python :: 3.11
Classifier: Topic :: Scientific/Engineering :: Artificial Intelligence
Classifier: Topic :: Software Development :: Libraries
Requires-Python: >=3.8
Requires-Dist: numpy>=1.21.0
Requires-Dist: pandas>=1.3.0
Requires-Dist: scikit-learn>=1.0.0
Requires-Dist: matplotlib>=3.4.0
Requires-Dist: seaborn>=0.11.0
Provides-Extra: ml-extra
Requires-Dist: tensorflow>=2.10.0; extra == "ml-extra"
Requires-Dist: torch>=1.12.0; extra == "ml-extra"
Requires-Dist: xgboost>=1.7.0; extra == "ml-extra"
Requires-Dist: lightgbm>=3.3.0; extra == "ml-extra"
Provides-Extra: dev
Requires-Dist: pytest>=7.0; extra == "dev"
Requires-Dist: pytest-cov>=3.0; extra == "dev"
Requires-Dist: black>=22.0; extra == "dev"
Requires-Dist: flake8>=4.0; extra == "dev"
Requires-Dist: mypy>=0.950; extra == "dev"
